slamifest/__about__.py
slamifest/__init__.py
slamifest/__main__.py
slamifest/tokens.py
slamifest/cli/__init__.py
slamifest-1.0.0.dist-info/METADATA
slamifest-1.0.0.dist-info/WHEEL
slamifest-1.0.0.dist-info/entry_points.txt
slamifest-1.0.0.dist-info/licenses/LICENSE.txt
slamifest-1.0.0.dist-info/RECORD
