Metadata-Version: 2.1
Name: slamifest
Version: 1.0.0
Project-URL: Documentation, https://github.com/hreeder/slamifest#readme
Project-URL: Issues, https://github.com/hreeder/slamifest/issues
Project-URL: Source, https://github.com/hreeder/slamifest
Author-email: Harry Reeder <harry@harryreeder.co.uk>
License-Expression: MIT
License-File: LICENSE.txt
Classifier: Development Status :: 4 - Beta
Classifier: Programming Language :: Python
Classifier: Programming Language :: Python :: 3.8
Classifier: Programming Language :: Python :: 3.9
Classifier: Programming Language :: Python :: 3.10
Classifier: Programming Language :: Python :: 3.11
Classifier: Programming Language :: Python :: 3.12
Classifier: Programming Language :: Python :: Implementation :: CPython
Classifier: Programming Language :: Python :: Implementation :: PyPy
Requires-Python: >=3.8
Requires-Dist: click
Requires-Dist: halo
Requires-Dist: keyring
Requires-Dist: requests
